{
  "id": "kuvvet-ve-hareket",
  "baslik": "Kuvvet ve Hareket",
  "kazanimKodu": "FEN.2.2.2",
  "anlatim": {
    "ekranlar": [
      {
        "metin": "İleriye hareket için itme, kendimize doğru hareket için çekme kuvveti uygularız. Oyuncak kamyonu itince ilerler, çekince bize doğru gelir.",
        "gorsel": {
          "tur": "fen",
          "mod": "anlatim",
          "sahne": "kh-anlatim-1"
        }
      },
      {
        "metin": "Bisikletin pedallarını çevirdikçe hızlanır. Fren yapınca yavaşlar ve durur. Kuvvet hareketlileri de yavaşlatıp durdurabilir!",
        "gorsel": {
          "tur": "fen",
          "mod": "anlatim",
          "sahne": "kh-anlatim-2"
        }
      },
      {
        "metin": "Topa yan dokununca yön değiştirir. Hareket eden cisme kuvvet uyguladığımızda yönünü değiştirebiliriz.",
        "gorsel": {
          "tur": "fen",
          "mod": "anlatim",
          "sahne": "kh-anlatim-3"
        }
      }
    ]
  },
  "alistirma": [
    {
      "id": "kh-a1",
      "kazanimKodu": "FEN.2.2.2",
      "tip": "yazili",
      "soru": "Market arabasını ileri hareket ettirmek için ......... kuvveti uygularız.",
      "dogruCevap": "itme",
      "ipucu": "",
      "cevapTipi": "metin",
      "gorsel": {
        "tur": "fen",
        "mod": "nesne",
        "nesne": "market-arabasi"
      },
      "kazanim": "FEN.2.2.2"
    },
    {
      "id": "kh-a2",
      "kazanimKodu": "FEN.2.2.2",
      "tip": "yazili",
      "soru": "Çekmeceyi açmak için ......... kuvveti kullanırız.",
      "dogruCevap": "çekme",
      "ipucu": "",
      "cevapTipi": "metin",
      "gorsel": {
        "tur": "fen",
        "mod": "nesne",
        "nesne": "cekmece"
      },
      "kazanim": "FEN.2.2.2"
    },
    {
      "id": "kh-a3",
      "kazanimKodu": "FEN.2.2.2",
      "tip": "yazili",
      "soru": "Bisikleti durdurmak için frene bastığımızda bisiklet ......... yapar.",
      "dogruCevap": "yavaşlama",
      "ipucu": "",
      "cevapTipi": "metin",
      "gorsel": {
        "tur": "fen",
        "mod": "nesne",
        "nesne": "bisiklet"
      },
      "alternatifCevaplar": [
        "durma",
        "yavaşlar",
        "durur",
        "yavaşlama/durma"
      ],
      "kazanim": "FEN.2.2.2"
    },
    {
      "id": "kh-a4",
      "kazanimKodu": "FEN.2.2.2",
      "tip": "yazili",
      "soru": "Salıncağı ileriye göndermek için arkasından itme kuvveti uygularız.",
      "dogruCevap": "Doğru",
      "ipucu": "",
      "cevapTipi": "metin",
      "alternatifCevaplar": [
        "Evet",
        "evet",
        "doğru"
      ],
      "gorsel": {
        "tur": "fen",
        "mod": "nesne",
        "nesne": "salincak"
      },
      "kazanim": "FEN.2.2.2"
    },
    {
      "id": "kh-a5",
      "kazanimKodu": "FEN.2.2.2",
      "tip": "yazili",
      "soru": "Halat çekme oyununda çocuklar halatı ileri doğru iterler.",
      "dogruCevap": "Yanlış",
      "ipucu": "",
      "cevapTipi": "metin",
      "alternatifCevaplar": [
        "Hayır",
        "hayır",
        "yanlış"
      ],
      "gorsel": {
        "tur": "fen",
        "mod": "nesne",
        "nesne": "halat"
      },
      "kazanim": "FEN.2.2.2"
    },
    {
      "id": "kh-a6",
      "kazanimKodu": "FEN.2.2.2",
      "tip": "yazili",
      "soru": "Pinpon topuna raketimizle vurduğumuzda topun ......... değiştiririz.",
      "dogruCevap": "yönünü",
      "ipucu": "",
      "cevapTipi": "metin",
      "gorsel": {
        "tur": "fen",
        "mod": "nesne",
        "nesne": "raket"
      },
      "alternatifCevaplar": [
        "yön"
      ],
      "kazanim": "FEN.2.2.2"
    },
    {
      "id": "kh-a7",
      "kazanimKodu": "FEN.2.2.2",
      "tip": "yazili",
      "soru": "Lunaparktaki dönme dolabın yaptığı hareket ......... hareketidir.",
      "dogruCevap": "dönme",
      "ipucu": "",
      "cevapTipi": "metin",
      "gorsel": {
        "tur": "fen",
        "mod": "nesne",
        "nesne": "donme-dolap"
      },
      "kazanim": "FEN.2.2.2"
    },
    {
      "id": "kh-a8",
      "kazanimKodu": "FEN.2.2.2",
      "tip": "yazili",
      "soru": "Bebek arabasını kendimize doğru yaklaştırmak istiyorsak onu ......... .",
      "dogruCevap": "çekeriz",
      "ipucu": "",
      "cevapTipi": "metin",
      "gorsel": {
        "tur": "fen",
        "mod": "nesne",
        "nesne": "bebek-arabasi"
      },
      "alternatifCevaplar": [
        "çekme"
      ],
      "kazanim": "FEN.2.2.2"
    },
    {
      "id": "kh-a9",
      "kazanimKodu": "FEN.2.2.2",
      "tip": "yazili",
      "soru": "Rüzgar, rüzgargülüne çarparak ona dönme hareketi yaptırır.",
      "dogruCevap": "Doğru",
      "ipucu": "",
      "cevapTipi": "metin",
      "alternatifCevaplar": [
        "Evet",
        "evet",
        "doğru"
      ],
      "gorsel": {
        "tur": "fen",
        "mod": "nesne",
        "nesne": "ruzgar-gulu"
      },
      "kazanim": "FEN.2.2.2"
    },
    {
      "id": "kh-a10",
      "kazanimKodu": "FEN.2.2.2",
      "tip": "yazili",
      "soru": "Yerde duran bir top biz kuvvet uygulamadan kendi kendine zıplayabilir.",
      "dogruCevap": "Yanlış",
      "ipucu": "",
      "cevapTipi": "metin",
      "alternatifCevaplar": [
        "Hayır",
        "hayır",
        "yanlış"
      ],
      "gorsel": {
        "tur": "fen",
        "mod": "nesne",
        "nesne": "top"
      },
      "kazanim": "FEN.2.2.2"
    },
    {
      "id": "kh-a11",
      "kazanimKodu": "FEN.2.2.2",
      "tip": "yazili",
      "soru": "Yokuş aşağı serbest bırakılan oyuncak araba gittikçe ......... .",
      "dogruCevap": "hızlanır",
      "ipucu": "",
      "cevapTipi": "metin",
      "gorsel": {
        "tur": "fen",
        "mod": "nesne",
        "nesne": "araba"
      },
      "kazanim": "FEN.2.2.2"
    },
    {
      "id": "kh-a12",
      "kazanimKodu": "FEN.2.2.2",
      "tip": "yazili",
      "soru": "Zile basarken düğmeye ......... kuvveti uygularız.",
      "dogruCevap": "itme",
      "ipucu": "",
      "cevapTipi": "metin",
      "gorsel": {
        "tur": "fen",
        "mod": "nesne",
        "nesne": "zil"
      },
      "kazanim": "FEN.2.2.2"
    },
    {
      "id": "kh-a13",
      "kazanimKodu": "FEN.2.2.2",
      "tip": "yazili",
      "soru": "Fişi prizden çıkarmak için ......... kuvveti uygularız.",
      "dogruCevap": "çekme",
      "ipucu": "",
      "cevapTipi": "metin",
      "gorsel": {
        "tur": "fen",
        "mod": "nesne",
        "nesne": "fis"
      },
      "kazanim": "FEN.2.2.2"
    },
    {
      "id": "kh-a14",
      "kazanimKodu": "FEN.2.2.2",
      "tip": "yazili",
      "soru": "Okul otobüsü okula yaklaştığında hızlanma hareketi yapar.",
      "dogruCevap": "Yanlış",
      "ipucu": "",
      "cevapTipi": "metin",
      "alternatifCevaplar": [
        "Hayır",
        "hayır",
        "yanlış"
      ],
      "gorsel": {
        "tur": "fen",
        "mod": "nesne",
        "nesne": "otobus"
      },
      "kazanim": "FEN.2.2.2"
    },
    {
      "id": "kh-a15",
      "kazanimKodu": "FEN.2.2.2",
      "tip": "yazili",
      "soru": "Uçurtmanın ipini kendimize doğru ......... .",
      "dogruCevap": "çekeriz",
      "ipucu": "",
      "cevapTipi": "metin",
      "gorsel": {
        "tur": "fen",
        "mod": "nesne",
        "nesne": "ucurtma"
      },
      "alternatifCevaplar": [
        "çekme"
      ],
      "kazanim": "FEN.2.2.2"
    },
    {
      "id": "kh-a16",
      "kazanimKodu": "FEN.2.2.2",
      "tip": "yazili",
      "soru": "Çekiçle çivi çakarken çiviye itme kuvveti uygularız.",
      "dogruCevap": "Doğru",
      "ipucu": "",
      "cevapTipi": "metin",
      "alternatifCevaplar": [
        "Evet",
        "evet",
        "doğru"
      ],
      "gorsel": {
        "tur": "fen",
        "mod": "nesne",
        "nesne": "cekic"
      },
      "kazanim": "FEN.2.2.2"
    },
    {
      "id": "kh-a17",
      "kazanimKodu": "FEN.2.2.2",
      "tip": "yazili",
      "soru": "Çorabımızı giyerken onu yukarıya doğru ......... .",
      "dogruCevap": "çekeriz",
      "ipucu": "",
      "cevapTipi": "metin",
      "gorsel": {
        "tur": "fen",
        "mod": "nesne",
        "nesne": "corap"
      },
      "alternatifCevaplar": [
        "çekme"
      ],
      "kazanim": "FEN.2.2.2"
    },
    {
      "id": "kh-a18",
      "kazanimKodu": "FEN.2.2.2",
      "tip": "yazili",
      "soru": "Mıknatıs demir ataşlara ......... kuvveti uygular.",
      "dogruCevap": "çekme",
      "ipucu": "",
      "cevapTipi": "metin",
      "gorsel": {
        "tur": "fen",
        "mod": "nesne",
        "nesne": "miknatis"
      },
      "kazanim": "FEN.2.2.2"
    },
    {
      "id": "kh-a19",
      "kazanimKodu": "FEN.2.2.2",
      "tip": "yazili",
      "soru": "Gelen topu karşıya gönderen çocuk topa ......... kuvveti uygulamıştır.",
      "dogruCevap": "itme",
      "ipucu": "",
      "cevapTipi": "metin",
      "gorsel": {
        "tur": "fen",
        "mod": "nesne",
        "nesne": "voleybol"
      },
      "kazanim": "FEN.2.2.2"
    },
    {
      "id": "kh-a20",
      "kazanimKodu": "FEN.2.2.2",
      "tip": "yazili",
      "soru": "Duvara çarpıp geri gelen top ......... değiştirmiştir.",
      "dogruCevap": "yön",
      "ipucu": "",
      "cevapTipi": "metin",
      "gorsel": {
        "tur": "fen",
        "mod": "nesne",
        "nesne": "top"
      },
      "alternatifCevaplar": [
        "yönünü"
      ],
      "kazanim": "FEN.2.2.2"
    },
    {
      "id": "kh-a21",
      "kazanimKodu": "FEN.2.2.2",
      "tip": "yazili",
      "soru": "Duvar saatindeki yelkovan ve akrep sürekli ......... hareketi yapar.",
      "dogruCevap": "dönme",
      "ipucu": "",
      "cevapTipi": "metin",
      "gorsel": {
        "tur": "fen",
        "mod": "nesne",
        "nesne": "saat"
      },
      "kazanim": "FEN.2.2.2"
    },
    {
      "id": "kh-a22",
      "kazanimKodu": "FEN.2.2.2",
      "tip": "yazili",
      "soru": "Gözlüğü takarken yüzümüze doğru itme kuvvetiyle yerleştiririz.",
      "dogruCevap": "Doğru",
      "ipucu": "",
      "cevapTipi": "metin",
      "alternatifCevaplar": [
        "Evet",
        "evet",
        "doğru"
      ],
      "gorsel": {
        "tur": "fen",
        "mod": "nesne",
        "nesne": "gozluk"
      },
      "kazanim": "FEN.2.2.2"
    },
    {
      "id": "kh-a23",
      "kazanimKodu": "FEN.2.2.2",
      "tip": "yazili",
      "soru": "Tekerlekli valizi arkamızdan götürürken ona ......... kuvveti uygularız.",
      "dogruCevap": "çekme",
      "ipucu": "",
      "cevapTipi": "metin",
      "gorsel": {
        "tur": "fen",
        "mod": "nesne",
        "nesne": "valiz"
      },
      "kazanim": "FEN.2.2.2"
    },
    {
      "id": "kh-a24",
      "kazanimKodu": "FEN.2.2.2",
      "tip": "yazili",
      "soru": "Fırıldağa üflediğimizde fırıldak yavaşlar.",
      "dogruCevap": "Yanlış",
      "ipucu": "",
      "cevapTipi": "metin",
      "alternatifCevaplar": [
        "Hayır",
        "hayır",
        "yanlış"
      ],
      "gorsel": {
        "tur": "fen",
        "mod": "nesne",
        "nesne": "firildak"
      },
      "kazanim": "FEN.2.2.2"
    },
    {
      "id": "kh-a25",
      "kazanimKodu": "FEN.2.2.2",
      "tip": "yazili",
      "soru": "Trafik lambası yeşil yandığında arabalar ......... yapmaya başlar.",
      "dogruCevap": "hızlanma",
      "ipucu": "",
      "cevapTipi": "metin",
      "gorsel": {
        "tur": "fen",
        "mod": "nesne",
        "nesne": "trafik-isigi"
      },
      "alternatifCevaplar": [
        "hızlanır"
      ],
      "kazanim": "FEN.2.2.2"
    }
  ],
  "test": [
    {
      "id": "kh-t1",
      "kazanimKodu": "FEN.2.2.2",
      "tip": "coktanSecmeli",
      "soru": "Ayşe sepeti kendinden uzaklaştırarak hareket ettirdi. Hangi kuvveti uyguladı?",
      "dogruCevap": "İtme",
      "secenekler": [
        "İtme",
        "Çekme",
        "Yavaşlatma",
        "Döndürme"
      ],
      "ipucu": "",
      "kazanim": "FEN.2.2.2",
      "gorsel": {
        "tur": "fen",
        "mod": "nesne",
        "nesne": "market-arabasi"
      }
    },
    {
      "id": "kh-t2",
      "kazanimKodu": "FEN.2.2.2",
      "tip": "coktanSecmeli",
      "soru": "Yusuf fişi prizden çıkardı. Hangi kuvveti uyguladı?",
      "dogruCevap": "Çekme",
      "secenekler": [
        "Hızlandırma",
        "Dönme",
        "İtme",
        "Çekme"
      ],
      "ipucu": "",
      "kazanim": "FEN.2.2.2",
      "gorsel": {
        "tur": "fen",
        "mod": "nesne",
        "nesne": "fis"
      }
    },
    {
      "id": "kh-t3",
      "kazanimKodu": "FEN.2.2.2",
      "tip": "coktanSecmeli",
      "soru": "Yokuş aşağı giden bisiklet kendi kendine hangi hareketi yapar?",
      "dogruCevap": "Hızlanma",
      "secenekler": [
        "Hızlanma",
        "Yavaşlama",
        "Durma",
        "Dönme"
      ],
      "ipucu": "",
      "kazanim": "FEN.2.2.2",
      "gorsel": {
        "tur": "fen",
        "mod": "nesne",
        "nesne": "bisiklet"
      }
    },
    {
      "id": "kh-t4",
      "kazanimKodu": "FEN.2.2.2",
      "tip": "coktanSecmeli",
      "soru": "Şoför frenine basarak hangi hareketi yaptı?",
      "dogruCevap": "Yavaşlama ve durma",
      "secenekler": [
        "Hızlanma",
        "Yavaşlama ve durma",
        "Dönme",
        "Yön değiştirme"
      ],
      "ipucu": "",
      "kazanim": "FEN.2.2.2",
      "gorsel": {
        "tur": "fen",
        "mod": "nesne",
        "nesne": "araba"
      }
    },
    {
      "id": "kh-t5",
      "kazanimKodu": "FEN.2.2.2",
      "tip": "coktanSecmeli",
      "soru": "Can'ın topu çembere çarpıp geri döndü. Çemberle çarpışınca ne oldu?",
      "dogruCevap": "Yön değiştirdi",
      "secenekler": [
        "Hızlandı",
        "Yavaşladı",
        "Döndü",
        "Yön değiştirdi"
      ],
      "ipucu": "",
      "kazanim": "FEN.2.2.2",
      "gorsel": {
        "tur": "fen",
        "mod": "nesne",
        "nesne": "basketbol"
      }
    },
    {
      "id": "kh-t6",
      "kazanimKodu": "FEN.2.2.2",
      "tip": "coktanSecmeli",
      "soru": "Masadaki kitabı kendimize yaklaştırmak için ne yapmalıyız?",
      "dogruCevap": "Çekmeliyiz",
      "secenekler": [
        "Durdurmalıyız",
        "Döndürmeliyiz",
        "İtmeliyiz",
        "Çekmeliyiz"
      ],
      "ipucu": "",
      "kazanim": "FEN.2.2.2",
      "gorsel": {
        "tur": "fen",
        "mod": "nesne",
        "nesne": "kitap"
      }
    },
    {
      "id": "kh-t7",
      "kazanimKodu": "FEN.2.2.2",
      "tip": "coktanSecmeli",
      "soru": "Hande salıncağı ileriye gönderiyor. Ne uyguluyor?",
      "dogruCevap": "İtme kuvveti",
      "secenekler": [
        "Döndürme kuvveti",
        "Durdurucu kuvvet",
        "İtme kuvveti",
        "Çekme kuvveti"
      ],
      "ipucu": "",
      "kazanim": "FEN.2.2.2",
      "gorsel": {
        "tur": "fen",
        "mod": "nesne",
        "nesne": "salincak"
      }
    },
    {
      "id": "kh-t8",
      "kazanimKodu": "FEN.2.2.2",
      "tip": "coktanSecmeli",
      "soru": "Ali uçurtmanın uçmaması için ipe hangi kuvveti uyguluyor?",
      "dogruCevap": "Çekme",
      "secenekler": [
        "Döndürme",
        "Yavaşlatma",
        "İtme",
        "Çekme"
      ],
      "ipucu": "",
      "kazanim": "FEN.2.2.2",
      "gorsel": {
        "tur": "fen",
        "mod": "nesne",
        "nesne": "ucurtma"
      }
    },
    {
      "id": "kh-t9",
      "kazanimKodu": "FEN.2.2.2",
      "tip": "coktanSecmeli",
      "soru": "Virajlı yolda okul servisi ne yapmak zorundadır?",
      "dogruCevap": "Yön değiştirme",
      "secenekler": [
        "Çekme",
        "Dönme",
        "Yön değiştirme",
        "Hızlanma"
      ],
      "ipucu": "",
      "kazanim": "FEN.2.2.2",
      "gorsel": {
        "tur": "fen",
        "mod": "nesne",
        "nesne": "otobus"
      }
    },
    {
      "id": "kh-t10",
      "kazanimKodu": "FEN.2.2.2",
      "tip": "coktanSecmeli",
      "soru": "Direksiyonu sağa sola çevirdiğimizde direksiyonun hareketi nedir?",
      "dogruCevap": "Dönme",
      "secenekler": [
        "İtme",
        "Dönme",
        "Hızlanma",
        "Çekme"
      ],
      "ipucu": "",
      "kazanim": "FEN.2.2.2",
      "gorsel": {
        "tur": "fen",
        "mod": "nesne",
        "nesne": "direksiyon"
      }
    },
    {
      "id": "kh-t11",
      "kazanimKodu": "FEN.2.2.2",
      "tip": "coktanSecmeli",
      "soru": "Top havaya fırlatılınca en tepeye ulaşana kadar nasıl hareket eder?",
      "dogruCevap": "Giderek yavaşlar",
      "secenekler": [
        "Döner",
        "Giderek yavaşlar",
        "Giderek hızlanır",
        "Yön değiştirir"
      ],
      "ipucu": "",
      "kazanim": "FEN.2.2.2",
      "gorsel": {
        "tur": "fen",
        "mod": "nesne",
        "nesne": "top"
      }
    },
    {
      "id": "kh-t12",
      "kazanimKodu": "FEN.2.2.2",
      "tip": "coktanSecmeli",
      "soru": "Kaleci Mehmet topu elleriyle tuttu. Topun hareketini ne yaptı?",
      "dogruCevap": "Durdurdu",
      "secenekler": [
        "Hızlandırdı",
        "Döndürdü",
        "Durdurdu",
        "Yön değiştirdi"
      ],
      "ipucu": "",
      "kazanim": "FEN.2.2.2",
      "gorsel": {
        "tur": "fen",
        "mod": "nesne",
        "nesne": "kaleci"
      }
    },
    {
      "id": "kh-t13",
      "kazanimKodu": "FEN.2.2.2",
      "tip": "coktanSecmeli",
      "soru": "Rüzgargülünün hareketi nedir?",
      "dogruCevap": "Dönme",
      "secenekler": [
        "Yavaşlama",
        "Çekme",
        "Hızlanma",
        "Dönme"
      ],
      "ipucu": "",
      "kazanim": "FEN.2.2.2",
      "gorsel": {
        "tur": "fen",
        "mod": "nesne",
        "nesne": "ruzgar-gulu"
      }
    },
    {
      "id": "kh-t14",
      "kazanimKodu": "FEN.2.2.2",
      "tip": "coktanSecmeli",
      "soru": "Montumuzun fermuarını kapatmak için yukarı doğru ne yaparız?",
      "dogruCevap": "Çekeriz",
      "secenekler": [
        "Çekeriz",
        "Sıkıştırırız",
        "İteriz",
        "Döndürürüz"
      ],
      "ipucu": "",
      "kazanim": "FEN.2.2.2",
      "gorsel": {
        "tur": "fen",
        "mod": "nesne",
        "nesne": "mont"
      }
    },
    {
      "id": "kh-t15",
      "kazanimKodu": "FEN.2.2.2",
      "tip": "coktanSecmeli",
      "soru": "Fatma buzdolabı kapağını açtı. Kapağa hangi kuvveti uyguladı?",
      "dogruCevap": "Çekme",
      "secenekler": [
        "Çekme",
        "Dönme",
        "Yavaşlatma",
        "İtme"
      ],
      "ipucu": "",
      "kazanim": "FEN.2.2.2",
      "gorsel": {
        "tur": "fen",
        "mod": "nesne",
        "nesne": "buzdolabi"
      }
    },
    {
      "id": "kh-t16",
      "kazanimKodu": "FEN.2.2.2",
      "tip": "coktanSecmeli",
      "soru": "Limona sıkarken hangi kuvveti uygularız?",
      "dogruCevap": "İtme (Bastırma)",
      "secenekler": [
        "Hızlandırma",
        "İtme (Bastırma)",
        "Çekme",
        "Döndürme"
      ],
      "ipucu": "",
      "kazanim": "FEN.2.2.2",
      "gorsel": {
        "tur": "fen",
        "mod": "nesne",
        "nesne": "limon"
      }
    },
    {
      "id": "kh-t17",
      "kazanimKodu": "FEN.2.2.2",
      "tip": "coktanSecmeli",
      "soru": "Şemsiyeyi açarken sapı yukarı iteriz. Hangi kuvveti kullanırız?",
      "dogruCevap": "İtme",
      "secenekler": [
        "Çekme",
        "Durdurma",
        "İtme",
        "Yavaşlatma"
      ],
      "ipucu": "",
      "kazanim": "FEN.2.2.2",
      "gorsel": {
        "tur": "fen",
        "mod": "nesne",
        "nesne": "semsiye"
      }
    },
    {
      "id": "kh-t18",
      "kazanimKodu": "FEN.2.2.2",
      "tip": "coktanSecmeli",
      "soru": "Dalından kopan yaprak yere inerken hangi hareketi yapar?",
      "dogruCevap": "Hızlanma",
      "secenekler": [
        "Yukarı yön değiştirme",
        "Çekme",
        "Hızlanma",
        "Durma"
      ],
      "ipucu": "",
      "kazanim": "FEN.2.2.2",
      "gorsel": {
        "tur": "fen",
        "mod": "nesne",
        "nesne": "yaprak"
      }
    },
    {
      "id": "kh-t19",
      "kazanimKodu": "FEN.2.2.2",
      "tip": "coktanSecmeli",
      "soru": "Ali masayı duvara doğru uzaklaştırmak için ne uygular?",
      "dogruCevap": "İtme",
      "secenekler": [
        "İtme",
        "Dönme",
        "Sallama",
        "Çekme"
      ],
      "ipucu": "",
      "kazanim": "FEN.2.2.2",
      "gorsel": {
        "tur": "fen",
        "mod": "nesne",
        "nesne": "masa"
      }
    },
    {
      "id": "kh-t20",
      "kazanimKodu": "FEN.2.2.2",
      "tip": "coktanSecmeli",
      "soru": "Süpürgeyi hem ileri ... hem geri ... . Boşluklara ne gelir?",
      "dogruCevap": "İter - Çeker",
      "secenekler": [
        "Döndürür - İter",
        "İter - Çeker",
        "Çeker - İter",
        "İter - Döndürür"
      ],
      "ipucu": "",
      "kazanim": "FEN.2.2.2",
      "gorsel": {
        "tur": "fen",
        "mod": "nesne",
        "nesne": "supurge"
      }
    },
    {
      "id": "kh-t21",
      "kazanimKodu": "FEN.2.2.2",
      "tip": "coktanSecmeli",
      "soru": "Bağcıkları sıkıca bağlamak için ipleri kendimize doğru ne yaparız?",
      "dogruCevap": "Çekeriz",
      "secenekler": [
        "Yavaşlatırız",
        "Döndürürüz",
        "Çekeriz",
        "İteriz"
      ],
      "ipucu": "",
      "kazanim": "FEN.2.2.2",
      "gorsel": {
        "tur": "fen",
        "mod": "nesne",
        "nesne": "ayakkabi"
      }
    },
    {
      "id": "kh-t22",
      "kazanimKodu": "FEN.2.2.2",
      "tip": "coktanSecmeli",
      "soru": "Pili biten treni hareket ettirmek için parmağımızla hangi kuvveti uygularız?",
      "dogruCevap": "İtme",
      "secenekler": [
        "Durdurma",
        "Çekme",
        "Dönme",
        "İtme"
      ],
      "ipucu": "",
      "kazanim": "FEN.2.2.2",
      "gorsel": {
        "tur": "fen",
        "mod": "nesne",
        "nesne": "tren"
      }
    },
    {
      "id": "kh-t23",
      "kazanimKodu": "FEN.2.2.2",
      "tip": "coktanSecmeli",
      "soru": "Masa tenisinde top masaya çarptığında ne yapar?",
      "dogruCevap": "Yön değiştirir",
      "secenekler": [
        "Yavaşlar",
        "Durur",
        "Yön değiştirir",
        "Döner"
      ],
      "ipucu": "",
      "kazanim": "FEN.2.2.2",
      "gorsel": {
        "tur": "fen",
        "mod": "nesne",
        "nesne": "masa-tenisi"
      }
    },
    {
      "id": "kh-t24",
      "kazanimKodu": "FEN.2.2.2",
      "tip": "coktanSecmeli",
      "soru": "Küreği toprağa batıran Zeynep, küreğe ayağıyla hangi kuvveti uygular?",
      "dogruCevap": "İtme",
      "secenekler": [
        "İtme",
        "Yavaşlatma",
        "Döndürme",
        "Çekme"
      ],
      "ipucu": "",
      "kazanim": "FEN.2.2.2",
      "gorsel": {
        "tur": "fen",
        "mod": "nesne",
        "nesne": "kurek"
      }
    },
    {
      "id": "kh-t25",
      "kazanimKodu": "FEN.2.2.2",
      "tip": "coktanSecmeli",
      "soru": "Marangoz testereyi ileri iter ve kendine çeker. Hangi kuvvetleri kullanmış olur?",
      "dogruCevap": "İtme ve çekme",
      "secenekler": [
        "Yalnızca döndürme",
        "Sadece itme",
        "İtme ve çekme",
        "Sadece çekme"
      ],
      "ipucu": "",
      "kazanim": "FEN.2.2.2",
      "gorsel": {
        "tur": "fen",
        "mod": "nesne",
        "nesne": "testere"
      }
    }
  ]
}